django_templated_email_md-2025.10.1.dist-info/licenses/LICENSE
templated_email_md/__init__.py
templated_email_md/apps.py
templated_email_md/backend.py
templated_email_md/exceptions.py
templated_email_md/urls.py
templated_email_md/locale/es/LC_MESSAGES/django.mo
templated_email_md/locale/es/LC_MESSAGES/django.po
templated_email_md/migrations/__init__.py
templated_email_md/templates/templated_email/license.txt
templated_email_md/templates/templated_email/markdown_base.html
templated_email_md/templates/templated_email/markdown_styles.css
django_templated_email_md-2025.10.1.dist-info/METADATA
django_templated_email_md-2025.10.1.dist-info/WHEEL
django_templated_email_md-2025.10.1.dist-info/top_level.txt
django_templated_email_md-2025.10.1.dist-info/RECORD
