Metadata-Version: 2.4
Name: django-templated-email-md
Version: 2025.10.1
Summary: An extension for django-templated-email for creating emails with Markdown
Author-email: Jack Linke <jacklinke@gmail.com>
License-Expression: MIT
Project-URL: Homepage, https://github.com/OmenApps/django-templated-email-md
Project-URL: Repository, https://github.com/OmenApps/django-templated-email-md
Project-URL: Documentation, https://django-templated-email-md.readthedocs.io
Project-URL: Changelog, https://github.com/OmenApps/django-templated-email-md/releases
Classifier: Environment :: Web Environment
Classifier: Framework :: Django
Classifier: Framework :: Django :: 4.2
Classifier: Framework :: Django :: 5.0
Classifier: Framework :: Django :: 5.1
Classifier: Framework :: Django :: 5.2
Classifier: Development Status :: 4 - Beta
Classifier: Intended Audience :: Developers
Classifier: Operating System :: OS Independent
Classifier: Programming Language :: Python
Classifier: Programming Language :: Python :: 3
Classifier: Programming Language :: Python :: 3.11
Classifier: Programming Language :: Python :: 3.12
Classifier: Programming Language :: Python :: 3.13
Classifier: Programming Language :: Python :: 3.14
Classifier: Topic :: Communications :: Email
Classifier: Topic :: Software Development :: Libraries :: Python Modules
Requires-Python: <4.0,>=3.11
License-File: LICENSE
Requires-Dist: click~=8.1
Requires-Dist: django>=4.2.15
Requires-Dist: django-render-block~=0.8
Requires-Dist: django-templated-email~=3.0
Requires-Dist: html2text~=2024.2
Requires-Dist: markdown~=3.7
Requires-Dist: premailer~=3.10
Dynamic: license-file
